fastmcp_langchain_adaptor/__init__.py
fastmcp_langchain_adaptor/tools.py
fastmcp_langchain_adaptor-0.1.2.dist-info/METADATA
fastmcp_langchain_adaptor-0.1.2.dist-info/WHEEL
fastmcp_langchain_adaptor-0.1.2.dist-info/licenses/LICENSE
fastmcp_langchain_adaptor-0.1.2.dist-info/RECORD
