Metadata-Version: 2.4
Name: fastmcp-langchain-adaptor
Version: 0.1.2
Summary: Seamless integration between FastMCP and LangChain - convert MCP tools to LangChain StructuredTools
Project-URL: Homepage, https://github.com/username/fastmcp-langchain-adaptor
Project-URL: Repository, https://github.com/username/fastmcp-langchain-adaptor
Project-URL: Documentation, https://username.github.io/fastmcp-langchain-adaptor
Project-URL: Issues, https://github.com/username/fastmcp-langchain-adaptor/issues
Project-URL: Changelog, https://github.com/username/fastmcp-langchain-adaptor/blob/main/CHANGELOG.md
Author-email: Daniel Shea <daniel.shea@example.com>
Maintainer-email: Daniel Shea <daniel.shea@example.com>
License: MIT
License-File: LICENSE
Keywords: agents,ai,langchain,llm,mcp,model-context-protocol,tools
Classifier: Development Status :: 4 - Beta
Classifier: Intended Audience :: Developers
Classifier: License :: OSI Approved :: MIT License
Classifier: Operating System :: OS Independent
Classifier: Programming Language :: Python :: 3
Classifier: Programming Language :: Python :: 3.11
Classifier: Programming Language :: Python :: 3.12
Classifier: Topic :: Internet :: WWW/HTTP :: HTTP Servers
Classifier: Topic :: Scientific/Engineering :: Artificial Intelligence
Classifier: Topic :: Software Development :: Libraries :: Python Modules
Classifier: Typing :: Typed
Requires-Python: >=3.11
Requires-Dist: fastmcp>=2.12.4
Requires-Dist: langchain-core>=0.3.27
Requires-Dist: pydantic>=2.0.0
Provides-Extra: dev
Requires-Dist: bandit>=1.7.0; extra == 'dev'
Requires-Dist: black>=23.0.0; extra == 'dev'
Requires-Dist: build>=0.10.0; extra == 'dev'
Requires-Dist: mypy>=1.0.0; extra == 'dev'
Requires-Dist: pre-commit>=3.0.0; extra == 'dev'
Requires-Dist: pytest-asyncio>=0.21.0; extra == 'dev'
Requires-Dist: pytest-cov>=4.0.0; extra == 'dev'
Requires-Dist: pytest>=7.0.0; extra == 'dev'
Requires-Dist: ruff>=0.1.0; extra == 'dev'
Requires-Dist: safety>=2.0.0; extra == 'dev'
Requires-Dist: twine>=4.0.0; extra == 'dev'
Provides-Extra: docs
Requires-Dist: mkdocs-material>=9.0.0; extra == 'docs'
Requires-Dist: mkdocs>=1.5.0; extra == 'docs'
Requires-Dist: mkdocstrings[python]>=0.24.0; extra == 'docs'
Provides-Extra: test
Requires-Dist: pytest-asyncio>=0.21.0; extra == 'test'
Requires-Dist: pytest-cov>=4.0.0; extra == 'test'
Requires-Dist: pytest>=7.0.0; extra == 'test'
